cocos_map/DMD.py
cocos_map/Data.py
cocos_map/Grid.py
cocos_map/Inversion.py
cocos_map/Kalman.py
cocos_map/Main.py
cocos_map/Options.py
cocos_map/Plot.py
cocos_map/__init__.py
cocos_map/cli.py
cocos_map/cocos_map.py
cocos_map/optht.py
cocos_map/variableProj.py
cocos_map-0.1.0.dist-info/AUTHORS.rst
cocos_map-0.1.0.dist-info/LICENSE
cocos_map-0.1.0.dist-info/METADATA
cocos_map-0.1.0.dist-info/WHEEL
cocos_map-0.1.0.dist-info/entry_points.txt
cocos_map-0.1.0.dist-info/top_level.txt
cocos_map-0.1.0.dist-info/RECORD
