Metadata-Version: 2.1
Name: cocos-map
Version: 0.1.0
Summary: on-the-fly estimation of coastal paramters from video of a wave field
Home-page: https://github.com/MatthijsGawehn/cocos_map
Author: Matthijs Gawehn
Author-email: Matthijs.Gawehn@deltares.nl
License: GNU General Public License v3
Keywords: cocos_map
Platform: UNKNOWN
Classifier: Development Status :: 2 - Pre-Alpha
Classifier: Intended Audience :: Developers
Classifier: License :: OSI Approved :: GNU General Public License v3 (GPLv3)
Classifier: Natural Language :: English
Classifier: Programming Language :: Python :: 3
Classifier: Programming Language :: Python :: 3.6
Classifier: Programming Language :: Python :: 3.7
Classifier: Programming Language :: Python :: 3.8
Requires-Python: >=3.6
Requires-Dist: Click (>=7.0)
Requires-Dist: spyder (==5.1.5)
Requires-Dist: numpy (==1.20.3)
Requires-Dist: opencv-python (==4.1.2.30)
Requires-Dist: matplotlib (==3.3.1)
Requires-Dist: mat73 (==0.46)
Requires-Dist: scipy (==1.6.2)
Requires-Dist: joblib (==1.0.1)
Requires-Dist: scikit-image (==0.18.1)
